MANIFEST.in
README.md
requirements.txt
setup.cfg
setup.py
test-requires
iffylib/__init__.py
iffylib/cli.py
iffylib/client.py
iffylib/schema.py
iffylib.egg-info/PKG-INFO
iffylib.egg-info/SOURCES.txt
iffylib.egg-info/dependency_links.txt
iffylib.egg-info/entry_points.txt
iffylib.egg-info/requires.txt
iffylib.egg-info/top_level.txt