Metadata-Version: 1.1
Name: iffylib
Version: 0.0.1
Summary: CLI for giphy searches
Home-page: UNKNOWN
Author: jose idar
Author-email: jose.idar@gmail.com
License: UNKNOWN
Platform: UNKNOWN
Classifier: Development Status :: 4 - Beta
Classifier: Intended Audience :: Developers
Classifier: Natural Language :: English
Classifier: License :: Other/Proprietary License
Classifier: Operating System :: POSIX :: Linux
Classifier: Programming Language :: Python
Classifier: Programming Language :: Python :: 3.6
